vc2_conformance_data/__init__.py
vc2_conformance_data/berries.json
vc2_conformance_data/berries.raw
vc2_conformance_data/kingswood.json
vc2_conformance_data/kingswood.raw
vc2_conformance_data/pointer.json
vc2_conformance_data/pointer.raw
vc2_conformance_data/static_filter_analysis_bundle.zip
vc2_conformance_data/trees.json
vc2_conformance_data/trees.raw
vc2_conformance_data/version.py
vc2_conformance_data-1.0.0.dist-info/LICENSE.txt
vc2_conformance_data-1.0.0.dist-info/METADATA
vc2_conformance_data-1.0.0.dist-info/WHEEL
vc2_conformance_data-1.0.0.dist-info/entry_points.txt
vc2_conformance_data-1.0.0.dist-info/top_level.txt
vc2_conformance_data-1.0.0.dist-info/RECORD
